quickbase_model_maker/__init__.py
quickbase_model_maker/model_maker.py
quickbase_model_maker/utils.py
quickbase_model_maker-0.1.2.dist-info/METADATA
quickbase_model_maker-0.1.2.dist-info/WHEEL
quickbase_model_maker-0.1.2.dist-info/RECORD
