Metadata-Version: 2.1
Name: quickbase_model_maker
Version: 0.1.2
Summary: A lightweight model maker for quickbase
Project-URL: Homepage, https://github.com/robswc/quickbase-model-maker
Project-URL: Bug Tracker, https://github.com/robswc/quickbase-model-maker/issues
Author-email: Robert Carroll <robert.s.w.carroll@gmail.com>
Classifier: License :: OSI Approved :: MIT License
Classifier: Operating System :: OS Independent
Classifier: Programming Language :: Python :: 3
Requires-Python: >=3.7
